jchess/__init__.py
jchess/__main__.py
jchess/action.py
jchess/board.py
jchess/game.py
jchess/geometry.py
jchess/pieces.py
jchess/py.typed
jchess/run.py
jchess/display/__init__.py
jchess/display/_class.py
jchess/display/_configs.py
jchess/display/_constants.py
jchess/terminal/__init__.py
jchess/terminal/_linux.py
jchess/terminal/_windows.py
jchess-0.101.dist-info/METADATA
jchess-0.101.dist-info/WHEEL
jchess-0.101.dist-info/entry_points.txt
jchess-0.101.dist-info/licenses/LICENSE
jchess-0.101.dist-info/RECORD
