Metadata-Version: 2.1
Name: jchess
Version: 0.101
Summary: Chess in the command line.
Project-URL: Homepage, https://j-hil@github.com/j-hil/cli-chess.git
Author-email: j-hil <92876062+j-hil@users.noreply.github.com>
License: GNU General Public License v3 (GPLv3)
License-File: LICENSE
Keywords: chess,console,terminal
Classifier: Development Status :: 4 - Beta
Classifier: License :: OSI Approved :: GNU General Public License v3 (GPLv3)
Classifier: Operating System :: OS Independent
Classifier: Programming Language :: Python :: 3
Requires-Python: >=3.10
Requires-Dist: colorama<1,>=0.4.5
Provides-Extra: dev
Requires-Dist: autoflake<2,>=1.7.7; extra == 'dev'
Requires-Dist: black<23,>=22.8.0; extra == 'dev'
Requires-Dist: coverage[toml]<7,>=6.5.0; extra == 'dev'
Requires-Dist: flake8-pyproject<2,>=1.2.0; extra == 'dev'
Requires-Dist: ipykernel<7,>=6.17.0; extra == 'dev'
Requires-Dist: isort<6,>=5.10.1; extra == 'dev'
Requires-Dist: mypy<1,>=0.971; extra == 'dev'
Requires-Dist: pre-commit<3,>=2.20.0; extra == 'dev'
Requires-Dist: pydocstringformatter<1,>=0.7.2; extra == 'dev'
Requires-Dist: pydocstyle[toml]<7,>=6.1.1; extra == 'dev'
Requires-Dist: pylint<3,>=2.15.2; extra == 'dev'
Requires-Dist: pytest<8,>=7.2.0; extra == 'dev'
Requires-Dist: types-colorama<1,>=0.4.15; extra == 'dev'
